simplebar/__init__.py
simplebar/bar.py
simple_bar-0.0.2.dist-info/LICENSE
simple_bar-0.0.2.dist-info/METADATA
simple_bar-0.0.2.dist-info/WHEEL
simple_bar-0.0.2.dist-info/top_level.txt
simple_bar-0.0.2.dist-info/RECORD
