Metadata-Version: 2.1
Name: simple-bar
Version: 0.0.2
Summary: Simple Loading/Progress Bar for python
Home-page: UNKNOWN
Author: 4yub1k (Salah Ud Din)
Author-email: <salahuddin@protonmail.com>
License: UNKNOWN
Keywords: python,loading,progress,progress bar,upload bar
Platform: UNKNOWN
Classifier: Development Status :: 4 - Beta
Classifier: Intended Audience :: Developers
Classifier: Programming Language :: Python :: 3
Classifier: Operating System :: Unix
Classifier: Operating System :: MacOS :: MacOS X
Classifier: Operating System :: Microsoft :: Windows
License-File: LICENSE
